{
  "ticker": {
    "symbol": "PAXGUSDT",
    "priceChange": "-6.98000000",
    "priceChangePercent": "-0.171",
    "weightedAvgPrice": "4076.79074559",
    "prevClosePrice": "4080.70000000",
    "lastPrice": "4073.45000000",
    "lastQty": "0.28770000",
    "bidPrice": "4073.45000000",
    "bidQty": "0.55980000",
    "askPrice": "4073.46000000",
    "askQty": "1.28590000",
    "openPrice": "4080.43000000",
    "highPrice": "4081.69000000",
    "lowPrice": "4071.21000000",
    "volume": "689.97950000",
    "quoteVolume": "2812902.04024500",
    "openTime": 1782573729773,
    "closeTime": 1782660129773,
    "firstId": 48633318,
    "lastId": 48649959,
    "count": 16642
  },
  "strategy": {
    "signal": "waiting",
    "price": 4073.45,
    "reason": "監控中",
    "indicators": {
      "rsi": 22.1,
      "ema7": 4073.14,
      "ema25": 4074.56,
      "bbUpper": 4076.67,
      "bbMiddle": 4074.33,
      "bbLower": 4072
    }
  },
  "timestamp": 1782660136103
}