{
  "ticker": {
    "symbol": "PAXGUSDT",
    "priceChange": "-16.11000000",
    "priceChangePercent": "-0.395",
    "weightedAvgPrice": "4073.13655794",
    "prevClosePrice": "4073.88000000",
    "lastPrice": 4058.65,
    "lastQty": "0.16210000",
    "bidPrice": "4057.99000000",
    "bidQty": "1.98370000",
    "askPrice": "4058.00000000",
    "askQty": "0.64870000",
    "openPrice": "4074.76000000",
    "highPrice": 4081.64,
    "lowPrice": 4048.6,
    "volume": "1356.22960000",
    "quoteVolume": "5524108.36472000",
    "openTime": 1782603804965,
    "closeTime": 1782690204965,
    "firstId": 48638557,
    "lastId": 48665336,
    "count": 26780
  },
  "klines": [],
  "strategy": {
    "signal": "waiting",
    "price": 4058.65,
    "reason": "\u76e3\u63a7\u4e2d",
    "indicators": {
      "rsi": 50,
      "ema7": 4058.65,
      "ema25": 4058.65,
      "bbUpper": 4058.65,
      "bbMiddle": 4058.65,
      "bbLower": 4058.65
    }
  },
  "timestamp": 1782690205887
}