{
  "ticker": {
    "symbol": "PAXGUSDT",
    "priceChange": "-7.90000000",
    "priceChangePercent": "-0.194",
    "weightedAvgPrice": "4076.85112121",
    "prevClosePrice": "4080.71000000",
    "lastPrice": "4072.81000000",
    "lastQty": "0.28850000",
    "bidPrice": "4072.80000000",
    "bidQty": "2.18500000",
    "askPrice": "4072.81000000",
    "askQty": "0.00530000",
    "openPrice": "4080.71000000",
    "highPrice": "4082.00000000",
    "lowPrice": "4071.21000000",
    "volume": "693.49030000",
    "quoteVolume": "2827256.70710000",
    "openTime": 1782573074741,
    "closeTime": 1782659474741,
    "firstId": 48633235,
    "lastId": 48649898,
    "count": 16664
  },
  "strategy": {
    "signal": "waiting",
    "price": 4072.81,
    "reason": "監控中",
    "indicators": {
      "rsi": 12.27,
      "ema7": 4073.02,
      "ema25": 4074.78,
      "bbUpper": 4076.85,
      "bbMiddle": 4074.51,
      "bbLower": 4072.18
    }
  },
  "timestamp": 1782659475723
}